CHANGELOG.txt
LICENCE.txt
MANIFEST.in
README.md
setup.py
loliglio/__init__.py
loliglio.egg-info/PKG-INFO
loliglio.egg-info/SOURCES.txt
loliglio.egg-info/dependency_links.txt
loliglio.egg-info/top_level.txt