Metadata-Version: 2.1
Name: loliglio
Version: 0.0.4
Summary: Loliglio allows you to extract data from the Riot API easily for your app development. Loliglio Framework is also intuitive and free.
Home-page: https://conradofmf.gitbook.io/loliglio/
Author: Conrado Moreno
Author-email: cfmorenofernandez@gmail.com
License: BSD License
Keywords: lol,library,league-of-legends
Platform: UNKNOWN
Classifier: Development Status :: 5 - Production/Stable
Classifier: Intended Audience :: Developers
Classifier: Operating System :: OS Independent
Classifier: License :: OSI Approved :: BSD License
Classifier: Programming Language :: Python :: 3
License-File: LICENCE.txt
